gitinfo/gitinfo.py
gitinfo/utils.py
gitinfo-1.2.0.dist-info/LICENSE
gitinfo-1.2.0.dist-info/METADATA
gitinfo-1.2.0.dist-info/WHEEL
gitinfo-1.2.0.dist-info/entry_points.txt
gitinfo-1.2.0.dist-info/top_level.txt
gitinfo-1.2.0.dist-info/RECORD
