Metadata-Version: 2.1
Name: gitinfo
Version: 1.2.0
Summary: Quickly get information about a Github repository
Home-page: UNKNOWN
Author: Folke Ishii
Author-email: folke.ishii@gmail.com
License: MIT
Platform: UNKNOWN
Requires-Python: >=3.7
